{
    "1.4.4": {
        "Telegram bot": [
            "Fixed creating errorneous error posting attempt"
        ]
    },
    "1.4.3": {
        "Telegram bot": [
            "Fixed not sending an error post when encountering an error"
        ]
    },
    "1.4.2": {
        "Twitch bot": [
            "Changed bot to use logger instead of console"
        ]
    },
    "1.4.1": {
        "Twitch bot": [
            "Fixed bot to be actually loaded"
        ]
    },
    "1.4.0": {
        "General": [
            "added changelog",
            "added twitch bot"
        ],
        "Telegram bot": [
            "changed API version being fetched dynamically"
        ],
        "(NEW) Twitch bot": [
            "added basic functionality",
            "added '!mmr command"
        ]
    }
}